shipyard_salesforce/__init__.py
shipyard_salesforce/cli/__init__.py
shipyard_salesforce/cli/authtest.py
shipyard_salesforce/cli/csv_header_assist.py
shipyard_salesforce/cli/download.py
shipyard_salesforce/cli/upload.py
shipyard_salesforce/salesforce.py
shipyard_salesforce/salesforce_utils.py
shipyard_salesforce-0.1.1.dist-info/METADATA
shipyard_salesforce-0.1.1.dist-info/WHEEL
shipyard_salesforce-0.1.1.dist-info/RECORD
